bokeh_root_cmd/__init__.py
bokeh_root_cmd/main.py
bokeh_root_cmd/readycheck.py
bokeh_root_cmd-0.1.2.dist-info/LICENSE
bokeh_root_cmd-0.1.2.dist-info/METADATA
bokeh_root_cmd-0.1.2.dist-info/WHEEL
bokeh_root_cmd-0.1.2.dist-info/entry_points.txt
bokeh_root_cmd-0.1.2.dist-info/top_level.txt
bokeh_root_cmd-0.1.2.dist-info/RECORD
