Metadata-Version: 2.1
Name: bokeh-root-cmd
Version: 0.1.2
Summary: Command line wrapper to run a Bokeh script/folder at the root URL
Home-page: https://github.com/ideonate/bokeh-root-cmd
Author: Dan Lester
Author-email: dan@ideonate.com
License: UNKNOWN
Platform: UNKNOWN
Classifier: Programming Language :: Python :: 3
Classifier: License :: OSI Approved :: MIT License
Classifier: Operating System :: OS Independent
Requires-Python: >=3.6
Requires-Dist: Click (>=7.0)
